mspider/__init__.py
mspider/genspider.py
mspider/mtd.py
mspider/pp.py
mspider/spider.py
mspider/templates/spider_templ_based_Crawler.py
mspider/templates/spider_templ_based_MSpider.py
mspider-0.2.5.dist-info/LICENSE
mspider-0.2.5.dist-info/METADATA
mspider-0.2.5.dist-info/WHEEL
mspider-0.2.5.dist-info/entry_points.txt
mspider-0.2.5.dist-info/top_level.txt
mspider-0.2.5.dist-info/RECORD
