Metadata-Version: 2.1
Name: mspider
Version: 0.2.5
Summary: Make your spider multi-threaded.
Home-page: https://github.com/Tishacy/MSpider
Author: Tishacy
Author-email: 
License: UNKNOWN
Platform: UNKNOWN
Classifier: Programming Language :: Python :: 3
Classifier: Programming Language :: Python :: 3.5
Classifier: Programming Language :: Python :: 3.6
Classifier: Programming Language :: Python :: 3.7
Classifier: License :: OSI Approved :: MIT License
Classifier: Operating System :: OS Independent
Requires-Dist: numpy (>=1.14.4)
Requires-Dist: requests (>=2.18.4)
Requires-Dist: pandas (>=0.24.1)
Requires-Dist: tqdm (>=4.30.0)
Requires-Dist: wget (>=3.2)
Requires-Dist: beautifulsoup4 (>=4.7.1)
